py4paystack/__init__.py
py4paystack/paystack.py
py4paystack/routes/__init__.py
py4paystack/routes/apple_pay.py
py4paystack/routes/bulk_charges.py
py4paystack/routes/charge.py
py4paystack/routes/control_panel.py
py4paystack/routes/customers.py
py4paystack/routes/disputes.py
py4paystack/routes/invoices.py
py4paystack/routes/miscellaneous.py
py4paystack/routes/payment_pages.py
py4paystack/routes/plans.py
py4paystack/routes/products.py
py4paystack/routes/refund.py
py4paystack/routes/settlement.py
py4paystack/routes/subaccount.py
py4paystack/routes/subscription.py
py4paystack/routes/transactions.py
py4paystack/routes/transactions_split.py
py4paystack/routes/transfer_recipient.py
py4paystack/routes/transfers.py
py4paystack/routes/transfers_control.py
py4paystack/routes/verification.py
py4paystack/routes/virtual_accounts.py
py4paystack/utilities/__init__.py
py4paystack/utilities/decorators.py
py4paystack/utilities/errors.py
py4paystack/utilities/request.py
py4paystack/utilities/settings.py
py4paystack/utilities/util.py
py4paystack-1.0.1.dist-info/LICENSE
py4paystack-1.0.1.dist-info/METADATA
py4paystack-1.0.1.dist-info/WHEEL
py4paystack-1.0.1.dist-info/top_level.txt
py4paystack-1.0.1.dist-info/RECORD
