Metadata-Version: 2.1
Name: py4paystack
Version: 1.0.1
Summary: A paystack API wrapper in python with type checking functionality
Author-email: Raphael Ezeigwe <iraphael1308@gmail.com>
License: MIT License
Project-URL: Homepage, https://github.com/devRaphael13/pypaystack
Project-URL: Bug Tracker, https://github.com/devRaphael13/pypaystack/issues
Classifier: Programming Language :: Python :: 3
Classifier: License :: OSI Approved :: MIT License
Classifier: Operating System :: OS Independent
Requires-Python: >=3.9
License-File: LICENSE
